dapu/__init__.py
dapu/agents.yaml
dapu/context.py
dapu/downloader.py
dapu/drivers.yaml
dapu/enabler.py
dapu/fileops.py
dapu/job.py
dapu/jobstatus.py
dapu/maintenance.py
dapu/manager.py
dapu/observer.py
dapu/perks.py
dapu/placeholder.py
dapu/process.py
dapu/registrar.py
dapu/server.py
dapu/textops.py
dapu/versops.py
dapu/worker.py
dapu/agents/__init__.py
dapu/agents/agent.py
dapu/agents/agent_dig.py
dapu/agents/agent_drop.py
dapu/agents/agent_exceltartu.py
dapu/agents/agent_export.py
dapu/agents/agent_gen.py
dapu/agents/agent_history.py
dapu/agents/agent_import.py
dapu/agents/agent_map.py
dapu/agents/agent_runsql.py
dapu/agents/agent_shadow.py
dapu/agents/agent_stream.py
dapu/static/__init__.py
dapu/static/app.png
dapu/static/ikoon.txt
dapu/templates/__init__.py
dapu/templates/running.html
dapu/ver/__init__.py
dapu/ver/changes.yaml
dapu/ver/v000_a_dba.sql
dapu/ver/v000_b_ext.sql
dapu/ver/v001_schema.sql
dapu/ver/v002_registry.sql
dapu/ver/v003_stopper.sql
dapu/ver/v004_paused.sql
dapu/ver/v005_route_weight.sql
dapu/ver/v006_reg_disabled.sql
dapu/ver/xv004_route.sql
dapu/ver/xv005_to_date.sql
dapu/ver/xv006_date.sql
dapu/ver/xv007_overflow.sql
dapu-0.7.11.dist-info/METADATA
dapu-0.7.11.dist-info/WHEEL
dapu-0.7.11.dist-info/licenses/LICENSE copy.txt
dapu-0.7.11.dist-info/licenses/LICENSE.txt
dapu-0.7.11.dist-info/RECORD
