Metadata-Version: 2.4
Name: dapu
Version: 0.7.11
Summary: Definitions-based data loader
Author: Nauri Nastik
License-File: LICENSE copy.txt
License-File: LICENSE.txt
Classifier: License :: OSI Approved :: MIT License
Classifier: Operating System :: OS Independent
Classifier: Programming Language :: Python :: 3
Requires-Python: >=3.10
Requires-Dist: apprise
Requires-Dist: dbpoint
Requires-Dist: fastapi
Requires-Dist: jinja2
Requires-Dist: loguru
Requires-Dist: psutil
Requires-Dist: psycopg2-binary
Requires-Dist: pygelf
Requires-Dist: pyyaml
Requires-Dist: toml
Requires-Dist: uvicorn
